{
    "name": "StormX",
    "website": "https://stormx.io",
    "description": "Earn crypto when you shop online.",
    "explorer": "https://etherscan.io/token/0xa62cc35625b0c8dc1faea39d33625bb4c15bd71c",
    "symbol": "STMX",
    "decimals": 18,
    "status": "active",
    "links": [
        {
            "name": "twitter",
            "url": "https://twitter.com/Stormxio"
        },
        {
            "name": "telegram",
            "url": "https://t.me/stormxapp"
        },
        {
            "name": "reddit",
            "url": "https://reddit.com/stormxio/"
        }
    ],
    "network": "erc20",
    "identifier": "0xa62cc35625b0c8dc1faea39d33625bb4c15bd71c"
}