{
    "name": "Akropolis",
    "website": "https://akropolis.io",
    "description": "Akropolis describes itself as a domain-specific financial protocol dedicated to the needs of the informal economy.",
    "explorer": "https://etherscan.io/token/0x8Ab7404063Ec4DBcfd4598215992DC3F8EC853d7",
    "research": "https://research.binance.com/en/projects/akropolis",
    "symbol": "AKRO",
    "decimals": 18,
    "status": "active",
    "network": "erc20",
    "identifier": "0x8ab7404063ec4dbcfd4598215992dc3f8ec853d7"
}